argparsethis/__init__.py
argparsethis-1.1.2.dist-info/LICENSE
argparsethis-1.1.2.dist-info/METADATA
argparsethis-1.1.2.dist-info/WHEEL
argparsethis-1.1.2.dist-info/top_level.txt
argparsethis-1.1.2.dist-info/RECORD
