Metadata-Version: 2.1
Name: argparsethis
Version: 1.1.2
Summary: A drop-in replacement to Python's built-in argparse, that provides the capability to argparse any arbitrary string, not just command line arguments.
Home-page: https://gitlab.com/TheTwitchy/argparsethis
Author: TheTwitchy
Author-email: the.twitchy@gmail.com
License: UNKNOWN
Platform: UNKNOWN
Classifier: Programming Language :: Python :: 3
Classifier: License :: OSI Approved :: MIT License
Classifier: Operating System :: OS Independent
Requires-Python: >=3.6
